README.md
setup.py
syncit.py
syncit.egg-info/PKG-INFO
syncit.egg-info/SOURCES.txt
syncit.egg-info/dependency_links.txt
syncit.egg-info/top_level.txt