Metadata-Version: 1.2
Name: syncit
Version: 1.0.4
Summary: Extract synchronous functions from async coroutine functions using AST manipulation
Home-page: https://github.com/shhaumb/syncit
Author: Shubham Jain
Author-email: sj.iitr@gmail.com
License: MIT
Keywords: asyncio synchronous ast syncit
Platform: UNKNOWN
Requires-Python: >=3.5
